scnym/__init__.py
scnym/__main__.py
scnym/api.py
scnym/dataprep.py
scnym/interpret.py
scnym/main.py
scnym/model.py
scnym/predict.py
scnym/scnym_ad.py
scnym/trainer.py
scnym/utils.py
scnym-0.3.2.dist-info/LICENSE
scnym-0.3.2.dist-info/METADATA
scnym-0.3.2.dist-info/WHEEL
scnym-0.3.2.dist-info/entry_points.txt
scnym-0.3.2.dist-info/top_level.txt
scnym-0.3.2.dist-info/RECORD
